beamtools/__init__.py
beamtools/beam_profile.py
beamtools/common.py
beamtools/constants.py
beamtools/diffraction_grating_pair.py
beamtools/file_formats.py
beamtools/import_data_file.py
beamtools/prism_pair.py
beamtools/pulse.py
beamtools/sellmeier_dispersion.py
beamtools/spectrum_integrate.py
beamtools/tests.py
beamtools/ultrafast_pulse_propagation.py
beamtools-0.4.dist-info/DESCRIPTION.rst
beamtools-0.4.dist-info/METADATA
beamtools-0.4.dist-info/RECORD
beamtools-0.4.dist-info/WHEEL
beamtools-0.4.dist-info/metadata.json
beamtools-0.4.dist-info/top_level.txt
