Metadata-Version: 2.0
Name: beamtools
Version: 0.4
Summary: A suite of tools for the analysis of optical beams
Home-page: https://github.com/cpkm/beamtools
Author: Kyle Manchee
Author-email: cpkmanchee@gmail.com
License: UNKNOWN
Download-URL: https://github.com/cpkm/beamtools/archive/v0.4.tar.gz
Keywords: optics,analysis,beams,spectrum
Platform: any
